kinpy/__init__.py
kinpy/chain.py
kinpy/frame.py
kinpy/ik.py
kinpy/jacobian.py
kinpy/mjcf.py
kinpy/sdf.py
kinpy/transform.py
kinpy/urdf.py
kinpy/visualizer.py
kinpy/mjcf_parser/__init__.py
kinpy/mjcf_parser/attribute.py
kinpy/mjcf_parser/base.py
kinpy/mjcf_parser/constants.py
kinpy/mjcf_parser/copier.py
kinpy/mjcf_parser/debugging.py
kinpy/mjcf_parser/element.py
kinpy/mjcf_parser/io.py
kinpy/mjcf_parser/namescope.py
kinpy/mjcf_parser/parser.py
kinpy/mjcf_parser/schema.py
kinpy/mjcf_parser/util.py
kinpy/urdf_parser_py/__init__.py
kinpy/urdf_parser_py/sdf.py
kinpy/urdf_parser_py/urdf.py
kinpy/urdf_parser_py/xml_reflection/__init__.py
kinpy/urdf_parser_py/xml_reflection/basics.py
kinpy/urdf_parser_py/xml_reflection/core.py
kinpy/mjcf_parser/schema.xml
kinpy-0.5.5.dist-info/METADATA
kinpy-0.5.5.dist-info/WHEEL
kinpy-0.5.5.dist-info/licenses/LICENSE
kinpy-0.5.5.dist-info/RECORD
